kb_str/__init__.py
kb_str/kb_str.py
kb_str-0.0.2.dist-info/LICENSE
kb_str-0.0.2.dist-info/METADATA
kb_str-0.0.2.dist-info/WHEEL
kb_str-0.0.2.dist-info/top_level.txt
kb_str-0.0.2.dist-info/RECORD
