Metadata-Version: 2.1
Name: kb-str
Version: 0.0.2
Summary: A Python library for working with Kbc SAPI Client.
Author: pandyandy
Author-email: novakovadrea@gmail.com
Classifier: Programming Language :: Python :: 3
Classifier: License :: OSI Approved :: MIT License
Classifier: Operating System :: OS Independent
Classifier: Intended Audience :: Developers
Classifier: Intended Audience :: Information Technology
Classifier: Intended Audience :: Education
Classifier: Topic :: Software Development :: Libraries
Classifier: Topic :: Software Development :: Libraries :: Python Modules
Classifier: Development Status :: 5 - Production/Stable
Requires-Python: >=3.7
License-File: LICENSE
Requires-Dist: pygelf
Requires-Dist: pytz
Requires-Dist: deprecated
Requires-Dist: streamlit
Requires-Dist: pandas
Requires-Dist: kbcstorage
